LICENSE
MANIFEST.in
README.rst
setup.py
rdftransformer/__init__.py
rdftransformer/annotation.py
rdftransformer/coordinates.py
rdftransformer/evaluator.py
rdftransformer/helpers.py
rdftransformer/ontology.py
rdftransformer.egg-info/PKG-INFO
rdftransformer.egg-info/SOURCES.txt
rdftransformer.egg-info/dependency_links.txt
rdftransformer.egg-info/requires.txt
rdftransformer.egg-info/top_level.txt