Metadata-Version: 1.0
Name: rdftransformer
Version: 0.0.5
Summary: Annotation module for ALKIS Ontology
Home-page: https://github.com/edward18/annotationz
Author: Edward Dinu
Author-email: edward.dinu@fokus.fraunhofer.com
License: MIT License
